Workbook

Sheet START
A1: QUOTE CALCULATOR — Pressure Washing + Gutters
A2: Fill the yellow cells. Everything else calculates itself.
A4: Customer name | B4: Sample Customer
A5: Driveway / concrete (sq ft) | B5: 600
A6: House siding (sq ft) | B6: 1800
A7: Roof soft wash (sq ft) | B7: 0
A8: Gutters (linear ft) | B8: 150
A9: Stories (1-3) | B9: 2
A10: Price level (LOW / MID / HIGH) | B10: MID
A11: Your costs
A12: Round-trip miles | B12: 15
A13: Vehicle cost per mile ($) | B13: 0.7
A14: Chemicals & supplies ($) | B14: 45
A15: Crew hours (total, all people) | B15: 8
A16: Labor cost per hour ($) | B16: 40
A17: Target profit margin | B17: 0.4
A20: RESULT
A21: Quote price | B21: =CALC!B15
A22: Your total cost | B22: =CALC!B21
A23: Profit | B23: =B21-B22
A24: Profit margin | B24: =IF(B21=0,0,B23/B21)
A25: Price needed for target margin | B25: =IF(B17>=1,0,ROUNDUP(B22/(1-B17),-1))
A27: VERDICT | B27: =IF(B21=0,"Enter job sizes above",IF(B24>=B17,"OK - take the job",IF(B24>=B17-0.1,"LOW - quote "&TEXT(B25,"$#,##0")&" instead","REJECT - margin too thin, quote "&TEXT(B25,"$#,##0")&" or walk away")))
A29: Customer-ready quote text is on the COPY tab.

Sheet RATES
A1: Rates — edit to match your local market
A3: Key | B3: Service | C3: Unit | D3: LOW | E3: MID | F3: HIGH | G3: Source (2026)
A4: driveway | B4: Driveway / concrete | C4: $ / sq ft | D4: 0.15 | E4: 0.25 | F4: 0.4 | G4: Housecall Pro 2026: concrete $0.10-0.40/sq ft; driveway jobs $100-300
A5: house | B5: House wash (siding) | C5: $ / sq ft | D5: 0.2 | E5: 0.3 | F5: 0.45 | G5: 2026 cost guides: siding $0.20-0.60/sq ft; Housecall Pro house wash $250-800
A6: roof | B6: Roof soft wash | C6: $ / sq ft | D6: 0.25 | E6: 0.4 | F6: 0.9 | G6: 2026 cost guides: roof soft wash $0.15-0.90/sq ft, avg ~$0.35
A7: gutters | B7: Gutter cleaning (1 story) | C7: $ / linear ft | D7: 0.9 | E7: 1.2 | F7: 1.6 | G7: LeafFilter: $0.70-1.30/ft 1-story; Housecall Pro $0.80-2.00/ft
A10: Height multiplier (house wash + gutters)
A11: Stories | B11: Multiplier
A12: 1 | B12: 1 | C12: LeafFilter 2026: 2-story gutters cost ~1.3-1.9x 1-story
A13: 2 | B13: 1.35
A14: 3 | B14: 1.7
A16: Minimum job charge | B16: 150 | C16: Housecall Pro 2026: most jobs $150-500
A18: Ranges are national averages. Replace them with what your area pays — the calculator uses whatever you type here.

Sheet CALC
A1: Calculations (no need to edit)
A3: Price column | B3: =MATCH(START!B10,RATES!D3:F3,0)
A4: Height multiplier | B4: =VLOOKUP(START!B9,RATES!A12:B14,2,FALSE)
A6: Line item | B6: Amount | C6: Rate | D6: Qty
A7: Driveway / concrete | B7: =ROUND(C7*D7,2) | C7: =INDEX(RATES!D4:F4,1,$B$3) | D7: =START!B5
A8: House wash | B8: =ROUND(C8*D8*$B$4,2) | C8: =INDEX(RATES!D5:F5,1,$B$3) | D8: =START!B6
A9: Roof soft wash | B9: =ROUND(C9*D9,2) | C9: =INDEX(RATES!D6:F6,1,$B$3) | D9: =START!B7
A10: Gutter cleaning | B10: =ROUND(C10*D10*$B$4,2) | C10: =INDEX(RATES!D7:F7,1,$B$3) | D10: =START!B8
A12: Subtotal | B12: =SUM(B7:B10)
A13: Minimum job charge | B13: =RATES!B16
A14: Minimum applied? | B14: =IF(AND(B12>0,B12<B13),"YES","no")
A15: QUOTE PRICE | B15: =IF(B12=0,0,ROUND(MAX(B12,B13),0))
A17: Labor | B17: =START!B15*START!B16
A18: Travel | B18: =START!B12*START!B13
A19: Chemicals & supplies | B19: =START!B14
A21: TOTAL COST | B21: =SUM(B17:B19)

Sheet COPY
A1: Customer quote — copy into your text / email
A3: ="Hi "&START!B4&","
A4: ="Thanks for reaching out. Here is your quote:"
A5: =IF(CALC!B7>0,"- Driveway / concrete ("&START!B5&" sq ft): "&TEXT(CALC!B7,"$#,##0"),"")
A6: =IF(CALC!B8>0,"- House wash ("&START!B6&" sq ft, "&START!B9&"-story): "&TEXT(CALC!B8,"$#,##0"),"")
A7: =IF(CALC!B9>0,"- Roof soft wash ("&START!B7&" sq ft): "&TEXT(CALC!B9,"$#,##0"),"")
A8: =IF(CALC!B10>0,"- Gutter cleaning ("&START!B8&" ft): "&TEXT(CALC!B10,"$#,##0"),"")
A9: =IF(CALC!B14="YES","- Minimum service charge applies","")
A10: ="TOTAL: "&TEXT(CALC!B15,"$#,##0")
A11: ="This quote is valid for 30 days. Reply YES and I will send available dates."
